senweaver/__init__.py
senweaver/__version__.py
senweaver/core.py
senweaver-0.0.1.dist-info/METADATA
senweaver-0.0.1.dist-info/WHEEL
senweaver-0.0.1.dist-info/top_level.txt
senweaver-0.0.1.dist-info/RECORD
