Metadata-Version: 2.1
Name: senweaver
Version: 0.0.1
Summary: data
Home-page: 
Author: sw
Author-email: 
License: MIT
Classifier: Programming Language :: Python :: 3
Classifier: License :: OSI Approved :: MIT License
Classifier: Operating System :: OS Independent
Requires-Python: >=3.9, <4
